easy_cozmo/__init__.py
easy_cozmo/actions_with_cubes.py
easy_cozmo/actions_with_custom_markers.py
easy_cozmo/actions_with_faces.py
easy_cozmo/actions_with_landmarks.py
easy_cozmo/actions_with_objects.py
easy_cozmo/animations.py
easy_cozmo/customcubes.py
easy_cozmo/defaults.py
easy_cozmo/easy_cozmo.py
easy_cozmo/initialize_robot.py
easy_cozmo/line_detection_utils.py
easy_cozmo/line_detector.py
easy_cozmo/movements.py
easy_cozmo/odometry.py
easy_cozmo/robot_utils.py
easy_cozmo/say.py
easy_cozmo-1.0.0.dist-info/METADATA
easy_cozmo-1.0.0.dist-info/WHEEL
easy_cozmo-1.0.0.dist-info/top_level.txt
easy_cozmo-1.0.0.dist-info/RECORD
