Metadata-Version: 2.1
Name: easy-cozmo
Version: 1.0.0
Summary: Useful python wrappers for Cozmo SDK.
Home-page: http://pypi.python.org/pypi/easy_cozmo
Author: Eduardo Feo-Flushing
Author-email: efeoflus@andrew.cmu.edu
License: LICENSE.txt
Platform: UNKNOWN
Requires-Dist: numpy (>=1.12)
Requires-Dist: cozmo (>=1.4.4)
Requires-Dist: opencv-python (>=3.1)
